Metadata-Version: 2.1
Name: plag
Version: 0.1
Summary: Search for clones of code in the texts of computer programs
Home-page: UNKNOWN
Author-email: d.e.cherkasov@mail.ru
License: UNKNOWN
Platform: UNKNOWN
